Metadata-Version: 2.1
Name: hrsd-django-chunkator
Version: 2.2.1
Summary: Fake Django Chunkator for POC purposes
Author: Julien Miotte
Author-email: j.miotte@majerti.fr
Classifier: Programming Language :: Python :: 3
Classifier: License :: OSI Approved :: MIT License
Classifier: Operating System :: OS Independent
Requires-Python: >=3.6
